sphinx_remove_toctrees/__init__.py
sphinx_remove_toctrees-0.0.3.dist-info/LICENSE
sphinx_remove_toctrees-0.0.3.dist-info/METADATA
sphinx_remove_toctrees-0.0.3.dist-info/WHEEL
sphinx_remove_toctrees-0.0.3.dist-info/top_level.txt
sphinx_remove_toctrees-0.0.3.dist-info/RECORD
