Metadata-Version: 2.1
Name: sphinx-remove-toctrees
Version: 0.0.3
Summary: Reduce your documentation build size by selectively removing toctrees from pages.
Home-page: https://github.com/executablebooks/sphinx-remove-toctrees
Author: Executable Book Project
License: MIT License
Platform: UNKNOWN
Classifier: License :: OSI Approved :: MIT License
Classifier: Programming Language :: Python :: 3
Classifier: Programming Language :: Python :: 3.6
Classifier: Programming Language :: Python :: 3.7
Classifier: Programming Language :: Python :: 3.8
Classifier: Programming Language :: Python :: 3.9
Classifier: Programming Language :: Python :: 3 :: Only
Requires-Python: >=3.6
Provides-Extra: code_style
Provides-Extra: docs
Provides-Extra: tests
